compare_pdf/__init__.py
compare_pdf/compare_pdf.py
compare_pdf-0.2.dist-info/LICENSE
compare_pdf-0.2.dist-info/METADATA
compare_pdf-0.2.dist-info/WHEEL
compare_pdf-0.2.dist-info/entry_points.txt
compare_pdf-0.2.dist-info/top_level.txt
compare_pdf-0.2.dist-info/RECORD
