Metadata-Version: 2.1
Name: compare_pdf
Version: 0.2
Summary: A simple package to visually compare PDF files
Author: Mor Dabastany
Author-email: morpci@gmail.com
License-File: LICENSE
Requires-Dist: PyMuPDF
Requires-Dist: opencv-python
